tcrpmhcdataset/TCR.py
tcrpmhcdataset/__init__.py
tcrpmhcdataset/constants.py
tcrpmhcdataset/dataset.py
tcrpmhcdataset/pMHC.py
tcrpmhcdataset/refs/2field_hla_consensus_seqs.csv
tcrpmhcdataset/refs/hla_pseudo_seqs.csv
tcrpmhcdataset-0.1.2.dist-info/LICENSE
tcrpmhcdataset-0.1.2.dist-info/METADATA
tcrpmhcdataset-0.1.2.dist-info/WHEEL
tcrpmhcdataset-0.1.2.dist-info/top_level.txt
tcrpmhcdataset-0.1.2.dist-info/RECORD
