Metadata-Version: 2.1
Name: tcrpmhcdataset
Version: 0.1.2
Summary: Handling Many-to-many TCR::Peptide-MHC Data
Author-email: Dhuvi Karthikeyan <dkarthikeyan@berkeley.edu>
Project-URL: Homepage, https://github.com/pirl-unc/TCRpMHCdataset
Project-URL: Bug Tracker, https://github.com/pirl-unc/TCRpMHCdataset/issues
Project-URL: Documentation, https://pirl-unc.github.io/TCRpMHCdataset/tcrpmhcdataset.html
Keywords: immunoinformatics,T-cell Receptor,machine learning,bioinformatics,peptide-MHC,TCR,immunology,data handling
Classifier: Programming Language :: Python :: Implementation :: CPython
Classifier: Environment :: Console
Classifier: Operating System :: OS Independent
Classifier: Intended Audience :: Science/Research
Classifier: License :: OSI Approved :: Apache Software License
Classifier: Topic :: Scientific/Engineering :: Bio-Informatics
Requires-Python: >=3.7
License-File: LICENSE
Requires-Dist: pandas <3.0.0,>=2.0.0
Requires-Dist: numpy <2.0.0,>=1.0.0
Requires-Dist: scikit-learn <2.0.0,>=1.0.0
Requires-Dist: mhcgnomes <2.0.0,>=1.5.0
Requires-Dist: tidytcells <3.0.0,>=2.0.0
